ensync_core/__init__.py
ensync_core/ecc_crypto.py
ensync_core/error.py
ensync_core/payload_utils.py
ensync_core-0.1.2.dist-info/METADATA
ensync_core-0.1.2.dist-info/WHEEL
ensync_core-0.1.2.dist-info/top_level.txt
ensync_core-0.1.2.dist-info/RECORD
