Metadata-Version: 2.4
Name: ensync-core
Version: 0.1.2
Summary: Core utilities for EnSync SDK - encryption, decryption, and error handling
Home-page: https://github.com/EnSync-engine/Python-SDK
Author: EnSync Team
Author-email: dev@ensync.cloud
Keywords: ensync,encryption,utilities
Classifier: Development Status :: 4 - Beta
Classifier: Intended Audience :: Developers
Classifier: License :: OSI Approved :: MIT License
Classifier: Programming Language :: Python :: 3
Classifier: Programming Language :: Python :: 3.7
Classifier: Programming Language :: Python :: 3.8
Classifier: Programming Language :: Python :: 3.9
Classifier: Programming Language :: Python :: 3.10
Classifier: Programming Language :: Python :: 3.11
Requires-Python: >=3.7
Requires-Dist: pynacl>=1.5.0
Dynamic: author
Dynamic: author-email
Dynamic: classifier
Dynamic: description
Dynamic: description-content-type
Dynamic: home-page
Dynamic: keywords
Dynamic: requires-dist
Dynamic: requires-python
Dynamic: summary
